{
	"name": "water",
	"plugin-id": "Sprite",
	"sid": 761134569793293,
	"isGlobal": false,
	"instanceVariables": [],
	"behaviorTypes": [
		{
			"behaviorId": "Bullet",
			"name": "Bullet",
			"sid": 869270702051168
		}
	],
	"effectTypes": [],
	"animations": {
		"items": [
			{
				"frames": [
					{
						"width": 60,
						"height": 71,
						"originX": 0.5583333333333333,
						"originY": 0.5,
						"originalSource": "",
						"exportFormat": "png",
						"exportQuality": 0.8,
						"imageSpriteId": 4673806,
						"collisionPoly": {
							"points": [
								0.27202380952380967,
								0.2633579253297564,
								0.8000000000000003,
								0.06438631790744466,
								0.7142857142857153,
								0.48871003800581353,
								1,
								1,
								1,
								1,
								1,
								1,
								0.014880952380952377,
								0.907444668008048,
								0.1339285714285714,
								0.6861167002012052
							]
						},
						"useCollisionPoly": true,
						"duration": 1
					},
					{
						"width": 66,
						"height": 74,
						"originX": 0.5,
						"originY": 0.5,
						"originalSource": "",
						"exportFormat": "png",
						"exportQuality": 0.8,
						"imageSpriteId": 33467,
						"collisionPoly": {
							"points": [
								0.19264069264069256,
								0.528957528957529,
								0.326839826839827,
								0.26640926640926643,
								0.8290043290043283,
								0.08880308880308874,
								0.6904761904761915,
								0.5231660231660241,
								0.8203463203463212,
								0.9285714285714287,
								0.3311688311688313,
								0.9864864864864865,
								0.14069264069264079,
								0.9169884169884172,
								0.0735930735930736,
								0.8243243243243247
							]
						},
						"useCollisionPoly": true,
						"duration": 1
					},
					{
						"width": 64,
						"height": 73,
						"originX": 0.5,
						"originY": 0.5,
						"originalSource": "",
						"exportFormat": "png",
						"exportQuality": 0.8,
						"imageSpriteId": 4075570,
						"collisionPoly": {
							"points": [
								0.43750000000000056,
								0.11545988258317025,
								0.8035714285714293,
								0.04892367906066536,
								0.9151785714285717,
								0.17416829745596868,
								0.6696428571428582,
								0.31115459882583174,
								0.7142857142857152,
								0.5968688845401174,
								0.8616071428571433,
								0.9412915851272016,
								0.28125000000000033,
								0.9882583170254403,
								0.1339285714285715,
								0.7495107632093934
							]
						},
						"useCollisionPoly": true,
						"duration": 1
					},
					{
						"width": 63,
						"height": 74,
						"originX": 0.5,
						"originY": 0.5,
						"originalSource": "",
						"exportFormat": "png",
						"exportQuality": 0.8,
						"imageSpriteId": 8512229,
						"collisionPoly": {
							"points": [
								0.1904761904761904,
								0.527027027027027,
								0.3027210884353742,
								0.29536679536679533,
								0.8367346938775515,
								0.11776061776061776,
								0.6553287981859417,
								0.5096525096525106,
								0.8367346938775508,
								0.9266409266409268,
								0.2709750566893424,
								0.9575289575289576,
								0.14058956916099768,
								0.9111969111969114,
								0.0634920634920635,
								0.868725868725869
							]
						},
						"useCollisionPoly": true,
						"duration": 1
					},
					{
						"width": 63,
						"height": 74,
						"originX": 0.5,
						"originY": 0.5,
						"originalSource": "",
						"exportFormat": "png",
						"exportQuality": 0.8,
						"imageSpriteId": 2954487,
						"collisionPoly": {
							"points": [
								0.21315192743764172,
								0.4691119691119692,
								0.3662131519274378,
								0.20270270270270263,
								0.8276643990929714,
								0.11003861003861004,
								0.6281179138321998,
								0.440154440154441,
								0.8548752834467127,
								0.9382239382239383,
								0.3390022675736963,
								0.972972972972973,
								0.14965986394557818,
								0.9227799227799229,
								0.04081632653061225,
								0.895752895752896
							]
						},
						"useCollisionPoly": true,
						"duration": 1
					},
					{
						"width": 64,
						"height": 64,
						"originX": 0.5,
						"originY": 0.5,
						"originalSource": "",
						"exportFormat": "png",
						"exportQuality": 0.8,
						"imageSpriteId": 2553470,
						"collisionPoly": {
							"points": [
								0.390625,
								0.23214285714285723,
								0.8348214285714284,
								0.03571428571428577,
								0.9017857142857144,
								0.16517857142857154,
								0.6339285714285724,
								0.3705357142857149,
								0.6964285714285724,
								0.6071428571428577,
								0.9062500000000002,
								0.9330357142857147,
								0.1227678571428571,
								0.9464285714285716,
								0.1986607142857144,
								0.5535714285714302
							]
						},
						"useCollisionPoly": true,
						"duration": 1
					},
					{
						"width": 76,
						"height": 62,
						"originX": 0.5,
						"originY": 0.5,
						"originalSource": "",
						"exportFormat": "png",
						"exportQuality": 0.8,
						"imageSpriteId": 835004,
						"collisionPoly": {
							"points": [
								0.2593984962406015,
								0.31797235023041454,
								0.5949248120300754,
								0.1290322580645161,
								0.8270676691729318,
								0.19354838709677413,
								0.6729323308270664,
								0.36866359447004615,
								0.6203007518796987,
								0.5990783410138244,
								0.6851503759398488,
								0.9354838709677422,
								0.09774436090225563,
								0.9078341013824885,
								0.041353383458646614,
								0.7880184331797244
							]
						},
						"useCollisionPoly": true,
						"duration": 1
					},
					{
						"width": 66,
						"height": 74,
						"originX": 0.5,
						"originY": 0.5,
						"originalSource": "",
						"exportFormat": "png",
						"exportQuality": 0.8,
						"imageSpriteId": 1577116,
						"collisionPoly": {
							"points": [
								0.23160173160173142,
								0.5366795366795362,
								0.48268398268398305,
								0.216216216216216,
								0.8116883116883118,
								0.17760617760617764,
								0.6774891774891779,
								0.500000000000001,
								0.7640692640692649,
								0.947876447876448,
								0.31818181818181834,
								0.9671814671814672,
								0.18398268398268391,
								0.920849420849421,
								0.08874458874458878,
								0.8667953667953671
							]
						},
						"useCollisionPoly": true,
						"duration": 1
					},
					{
						"width": 88,
						"height": 65,
						"originX": 0.5,
						"originY": 0.5,
						"originalSource": "",
						"exportFormat": "png",
						"exportQuality": 0.8,
						"imageSpriteId": 9643452,
						"collisionPoly": {
							"points": [
								0.24512987012987036,
								0.47252747252747224,
								0.43993506493506496,
								0.2967032967032966,
								0.8327922077922078,
								0.20439560439560436,
								0.6477272727272736,
								0.45714285714285885,
								0.5665584415584414,
								0.8439560439560442,
								0.3198051948051943,
								0.8395604395604401,
								0.13474025974025974,
								0.8351648351648356,
								0.0698051948051948,
								0.8043956043956048
							]
						},
						"useCollisionPoly": true,
						"duration": 1
					}
				],
				"sid": 216955682138568,
				"name": "waves",
				"isLooping": true,
				"isPingPong": false,
				"repeatCount": 1,
				"repeatTo": 0,
				"speed": 5
			}
		],
		"subfolders": []
	}
}