{
	"name": "coin",
	"plugin-id": "Sprite",
	"sid": 311268460369236,
	"isGlobal": false,
	"instanceVariables": [],
	"behaviorTypes": [],
	"effectTypes": [],
	"animations": {
		"items": [
			{
				"frames": [
					{
						"width": 125,
						"height": 127,
						"originX": 0.472,
						"originY": 0.5118110236220472,
						"originalSource": "",
						"exportFormat": "png",
						"exportQuality": 0.8,
						"imageSpriteId": 2067388,
						"useCollisionPoly": true,
						"duration": 1
					},
					{
						"width": 125,
						"height": 127,
						"originX": 0.48,
						"originY": 0.952755905511811,
						"originalSource": "",
						"exportFormat": "png",
						"exportQuality": 0.8,
						"imageSpriteId": 1677622,
						"useCollisionPoly": true,
						"duration": 1
					}
				],
				"sid": 923420869610323,
				"name": "Animation 1",
				"isLooping": true,
				"isPingPong": false,
				"repeatCount": 1,
				"repeatTo": 0,
				"speed": 2
			}
		],
		"subfolders": []
	}
}